{"cameraMode":{"drawMode":0,"name":"Shaded","section":"Shading Mode"},"sceneLighting":false,"audioPlay":false,"sceneViewState":{"m_AlwaysRefresh":false,"showFog":true,"showSkybox":false,"showFlares":true,"showImageEffects":true,"showParticleSystems":true,"showVisualEffectGraphs":true,"m_FxEnabled":true},"in2DMode":false,"pivot":{"x":0.4188178777694702,"y":1.6441510915756226,"z":-0.33060115575790408},"rotation":{"x":0.2810743451118469,"y":-0.4958380460739136,"z":0.19165487587451936,"w":0.7991963028907776},"size":1.4198366403579713,"orthographic":false}